restraint/__init__.py
restraint/apps.py
restraint/constants.py
restraint/core.py
restraint/managers.py
restraint/models.py
restraint/signals.py
restraint/urls.py
restraint/version.py
restraint/management/__init__.py
restraint/management/commands/__init__.py
restraint/management/commands/update_restraint_db.py
restraint/migrations/0001_initial.py
restraint/migrations/0002_permset_is_private.py
restraint/migrations/0003_auto_20230301_0109.py
restraint/migrations/__init__.py
restraint/tests/__init__.py
restraint/tests/commands_tests.py
restraint/tests/configuration.py
restraint/tests/core_tests.py
restraint/tests/models_tests.py
django_restraint-2.3.0.dist-info/LICENSE
django_restraint-2.3.0.dist-info/METADATA
django_restraint-2.3.0.dist-info/WHEEL
django_restraint-2.3.0.dist-info/top_level.txt
django_restraint-2.3.0.dist-info/RECORD
